{
  "id": 26330,
  "title": "Jumping Frog",
  "time_limit": "1 초",
  "memory_limit": "1024 MB",
  "description": "<p>A frog is located at the coordinate (x<sub>1</sub>,y<sub>1</sub>). He wants to go to the coordinate (x<sub>2</sub>,y<sub>2</sub>). He will perform one or more jumps to reach his destination. The rule of the jumping is as follows: Suppose the frog is located at the coordinate (x,y); then he can jump to the following four squares:</p>\n<ol>\n<li>(x+y,y)</li>\n<li>(x-y,y)</li>\n<li>(x,y+x)</li>\n<li>(x,y-x)</li>\n</ol>\n<p>Given the coordinates (x<sub>1</sub>,y<sub>1</sub>) and (x<sub>2</sub>,y<sub>2</sub>), you need to determine if it is possible for the frog to travel from (x<sub>1</sub>,y<sub>1</sub>) to (x<sub>2</sub>,y<sub>2</sub>) through a series of jumps as described.</p>",
  "input": "<p>The first input line contains an integer, n (1 ≤ n ≤ 100), indicating the number of test cases. Each test case consists of four integers (between -1,000,000,000 to +1,000,000,000 inclusive) separated by a single space denoting x<sub>1</sub>, y<sub>1</sub>, x<sub>2</sub> and y<sub>2</sub>, respectively.</p>",
  "output": "<p>For each test case, output 1 if the frog can travel from (x<sub>1</sub>,y<sub>1</sub>) to (x<sub>2</sub>,y<sub>2</sub>) through a series of jumps as described or 0 otherwise.</p>",
  "samples": [
    {
      "input": "3\n-6 8 17 25\n13 17 -16 11\n0 0 5 6\n",
      "output": "0\n1\n0\n"
    }
  ],
  "hint": null,
  "source": "University, University of Central Florida, 2013 Local Programming Contest",
  "level": 8,
  "tags": ["math", "number_theory", "euclidean"],
  "accepted_user_count": 18,
  "submission_count": null,
  "average_tries": 1.333299994468689
}
