{
  "id": 1755,
  "title": "숫자놀이",
  "time_limit": "2 초",
  "memory_limit": "128 MB",
  "description": "<p>79를 영어로 읽되 숫자 단위로 하나씩 읽는다면 \"seven nine\"이 된다. 80은 마찬가지로 \"eight zero\"라고 읽는다. 79는 80보다 작지만, 영어로 숫자 하나씩 읽는다면 \"eight zero\"가 \"seven nine\"보다 사전순으로 먼저 온다.</p>\n<p>문제는 정수 M, N(1 ≤ M ≤ N ≤ 99)이 주어지면 M 이상 N 이하의 정수를 숫자 하나씩 읽었을 때를 기준으로 사전순으로 정렬하여 출력하는 것이다.</p>",
  "input": "<p>첫째 줄에 M과 N이 주어진다.</p>",
  "output": "<p>M 이상 N 이하의 정수를 문제 조건에 맞게 정렬하여 한 줄에 10개씩 출력한다.</p>",
  "samples": [
    {
      "input": "8 28\n",
      "output": "8 9 18 15 14 19 11 17 16 13\n12 10 28 25 24 21 27 26 23 22\n20\n"
    }
  ],
  "hint": null,
  "source": "author6, kjo7811, jh05013",
  "level": 7,
  "tags": ["string", "sorting"],
  "accepted_user_count": 4076,
  "submission_count": null,
  "average_tries": 1.5595999956130981
}
