[{"input": "8 3\n##K\n#..\n.#.\n###\n#.#\n##.\n##.\nH##\n", "output": "0\n"}, {"input": "2 3\n..H\nK##\n", "output": "1\n"}, {"input": "6 8\n........\n.#..H...\n#......#\n.#......\n........\n......K.\n", "output": "3\n"}, {"input": "5 8\n##..#.#.\nK.#..##.\n##.H#.#.\n####.##.\n#.##.#..\n", "output": "0\n"}, {"input": "9 3\n###\n##H\n##.\n##.\n##.\n##.\n##.\n...\nK##\n", "output": "1\n"}, {"input": "3 9\n.........\n..K...#..\n......H##\n", "output": "1\n"}, {"input": "7 8\n####.#K#\n.###.###\n###.#..#\n########\n##.###H#\n######..\n##...#.#\n", "output": "0\n"}, {"input": "2 4\n#..H\nK.##\n", "output": "1\n"}, {"input": "10 4\n##K#\n#.H#\n..#.\n#.#.\n###.\n....\n#.##\n###.\n####\n###.\n", "output": "-1\n"}, {"input": "9 10\n..##H.####\n.###.###.#\n.##...###.\n###.#...##\n.####.#K##\n###.#####.\n###.##.#.#\n#.########\n##.##..###\n", "output": "1\n"}, {"input": "4 10\n###.#.#..#\nH###.####.\nK#########\n#.#..####.\n", "output": "-1\n"}, {"input": "3 5\n..H..\n#..K#\n..#..\n", "output": "2\n"}, {"input": "2 5\n#.#..\n..KH.\n", "output": "-1\n"}, {"input": "10 2\n##\n##\n##\n##\n.K\n.#\n.#\nH#\n##\n##\n", "output": "1\n"}, {"input": "5 6\n.#.###\nK.####\n.#.#H#\n#..#..\n..###.\n", "output": "0\n"}, {"input": "9 6\n###.##\n#K.###\n...#.#\n.##..H\n######\n.###..\n...##.\n####.#\n#...##\n", "output": "0\n"}, {"input": "3 10\n######K###\n##########\n#H##.#.###\n", "output": "0\n"}, {"input": "7 10\n####H#####\n##########\n##########\n##########\n##K#######\n##########\n##########\n", "output": "0\n"}, {"input": "6 7\n.....#.\n.......\n.#..K..\n.....#.\n#..#...\n#.#H...\n", "output": "1\n"}, {"input": "10 3\n###\n#.#\n#H#\n..#\n#..\n..#\n#.#\nK..\n###\n###\n", "output": "1\n"}, {"input": "6 3\n.##\n..#\n.##\n.#.\n#.H\nK..\n", "output": "1\n"}, {"input": "9 4\n####\n####\nH...\n.##K\n####\n.###\n#..#\n####\n####\n", "output": "1\n"}, {"input": "4 3\n###\n###\n#H.\n##K\n", "output": "1\n"}, {"input": "3 7\n....H..\n.....#.\n.K.##..\n", "output": "2\n"}, {"input": "7 8\n.##.....\n.......K\n........\n#.......\n#..H#..#\n........\n....##.#\n", "output": "3\n"}, {"input": "6 8\n.#..##..\n.###...#\n.##.#..#\n.###.#.#\nK....H.#\n..#..#..\n", "output": "1\n"}, {"input": "5 9\n.........\n....#.K..\n.........\n.........\n..H......\n", "output": "3\n"}, {"input": "9 9\n.........\n....#....\n.#......#\n..##.#...\n.....##..\n###...H..\n#....#..K\n.......##\n.........\n", "output": "2\n"}, {"input": "8 3\n..#\n...\n.##\n#..\n..#\nH..\n..K\n.##\n", "output": "2\n"}, {"input": "4 10\n...H......\nK.........\n......#...\n...##...#.\n", "output": "3\n"}, {"input": "8 5\nK.#..\n#..#.\n##.#.\n##.##\n..###\n#..#.\n..#.#\n#H###\n", "output": "0\n"}, {"input": "2 5\nH####\n###.K\n", "output": "0\n"}, {"input": "6 6\n...K..\n.H..#.\n......\n......\n......\n......\n", "output": "3\n"}, {"input": "5 9\n##....H..\n.#..#...#\n#.#.##...\n#.#K#..#.\n..#...##.\n", "output": "2\n"}, {"input": "4 6\nK.###.\n#....H\n#..#.#\n#.####\n", "output": "1\n"}, {"input": "3 10\n#####.##.K\n#####.#..#\n####.H...#\n", "output": "1\n"}, {"input": "8 10\n##########\n####H#####\n##########\n###.######\n##########\n##########\n##########\n#######K##\n", "output": "0\n"}, {"input": "3 2\n.H\n..\n.K\n", "output": "2\n"}, {"input": "6 6\n##.#..\n#..#.#\n##.#..\n##.###\n#####.\n##H..K\n", "output": "1\n"}, {"input": "7 2\n##\nK#\n.#\n.#\n.#\nH#\n##\n", "output": "1\n"}, {"input": "6 7\n#..##.#\n##.#.#.\n##....#\n...#.#.\n.##.###\n..H...K\n", "output": "1\n"}, {"input": "5 7\n#.####.\n#.##.#.\n#.#.#.#\n##.K..#\n###...H\n", "output": "1\n"}, {"input": "9 8\n########\n###K.###\n####.###\n####.##.\n####H###\n########\n########\n########\n########\n", "output": "1\n"}, {"input": "8 8\n........\n#.......\n........\n.H....#.\n......#.\n........\n........\n.#..K...\n", "output": "3\n"}, {"input": "7 7\n###..##\nK.#####\n.....##\n####.##\n####..H\n#.#####\n###.#.#\n", "output": "1\n"}, {"input": "6 3\n#.#\n###\n###\nH#.\n.K.\n#.#\n", "output": "1\n"}, {"input": "10 3\n...\n...\nH..\n..#\n...\n...\n...\n...\n...\n.#K\n", "output": "1\n"}, {"input": "5 3\nH.#\n...\n..#\n#.#\nK#.\n", "output": "0\n"}, {"input": "8 4\n##..\n#.##\n.###\n####\n#H.K\n####\n###.\n###.\n", "output": "1\n"}, {"input": "5 4\n....\n....\n....\n...H\n.K..\n", "output": "3\n"}]