{
  "id": 14272,
  "title": "f(X) = A + X + B + X + C",
  "time_limit": "2 초",
  "memory_limit": "512 MB",
  "description": "<p>f(X) = A + X + B + X + C로 정의되어 있는 함수가 있다. 여기서 X는 문자열이고, +는 문자열 연결을 나타내는 연산이다. A, B, C는 비어있지 않은 상수 문자열이다.</p>\n<p>다섯 문자열 A, B, C, S, F와 정수 K가 주어진다.</p>\n<p>이때, f<sup>K</sup>(S)에 F가 부분 문자열로 총 몇 번 등장하는지 구하는 프로그램을 작성하시오.</p>\n<p>f<sup>1</sup>(X) = f(X)이고, f<sup>K</sup>(X) = f(f<sup>K-1</sup>(X))와 같다.</p>",
  "input": "<p>첫째 줄에 A, B, C, S, F, K가 주어진다. A, B, C, S, F는 길이가 50보다 작거나 같은 알파벳 소문자로 이루어진 문자열이고, K는 10,000,000보다 작거나 같은 자연수이다.</p>",
  "output": "<p>첫째 줄에 f<sup>K</sup>(S)에 F가 부분 문자열로 등장하는 횟수의 1,000,000,007로 나눈 나머지를 출력한다. </p>",
  "samples": [
    {
      "input": "a b c x axb 2\n",
      "output": "2\n"
    },
    {
      "input": "a b c x abcdefghij 1\n",
      "output": "0\n"
    },
    {
      "input": "a b c d baadbdcbadbdccccbaaaadbdcbadbdccbaadbdcba 58\n",
      "output": "191690599\n"
    },
    {
      "input": "a x y b aaaaaaaaaaaaaaaaaaaaaaaaaaaaaaaaaaaaaaaaaaaaaaaaab 49\n",
      "output": "1\n"
    }
  ],
  "hint": null,
  "source": "baekjoon, eric00513",
  "level": 22,
  "tags": [
    "dp",
    "kmp",
    "string"
  ],
  "accepted_user_count": 7,
  "submission_count": null,
  "average_tries": 4
}