{
  "id": 4996,
  "title": "Water Tank",
  "time_limit": "1 초",
  "memory_limit": "128 MB",
  "description": "<p>Mr. Denjiro is a science teacher. Today he has just received a specially ordered water tank that will certainly be useful for his innovative experiments on water flow.</p>\n<p style=\"text-align: center;\"><img alt=\"\" src=\"/upload/images3/fig1.gif\" style=\"height:266px; width:431px\"/></p>\n<p style=\"text-align: center;\">Figure 1: The water tank</p>\n<p>The size of the tank is 100cm (Width) * 50cm (Height) * 30cm (Depth) (see Figure 1). For the experiments, he fits several partition boards inside of the tank parallel to the sideboards. The width of each board is equal to the depth of the tank, i.e. 30cm. The height of each board is less than that of the tank, i.e. 50 cm, and differs one another. The boards are so thin that he can neglect the thickness in the experiments.</p>\n<p style=\"text-align: center;\"><img alt=\"\" src=\"/upload/images3/fig2.gif\" style=\"height:233px; width:318px\"/></p>\n<p style=\"text-align: center;\">Figure 2: The front view of the tank</p>\n<p>The front view of the tank is shown in Figure 2.</p>\n<p>There are several faucets above the tank and he turns them on at the beginning of his experiment. The tank is initially empty. Your mission is to write a computer program to simulate water flow in the tank.</p>",
  "input": "<p>The input consists of multiple data sets. D is the number of the data sets.</p>\n<pre>\nD\nDataSet<sub>1</sub>\nDataSet<sub>2</sub>\n...\nDataSet<sub>D</sub></pre>\n<p>The format of each data set (DataSet<sub>d</sub> , 1 &lt;= d &lt;= D) is as follows.</p>\n<pre>\nN\nB<sub>1</sub> H<sub>1</sub>\nB<sub>2</sub> H<sub>2</sub>\n...\nB<sub>N</sub> H<sub>N</sub>\nM\nF<sub>1</sub> A<sub>1</sub>\nF<sub>2</sub> A<sub>2</sub>\n...\nF<sub>M</sub> A<sub>M</sub>\nL\nP<sub>1</sub> T<sub>1</sub>\nP<sub>2</sub> T<sub>2</sub>\n...\nP<sub>L</sub> T<sub>L</sub></pre>\n<p>Each line in the data set contains one or two integers.</p>\n<p>N is the number of the boards he sets in the tank . B<sub>i</sub> and H<sub>i</sub> are the x-position (cm) and the height (cm) of the i-th board, where 1 &lt;= i &lt;= N .</p>\n<p>H<sub>i</sub> s differ from one another. You may assume the following.</p>\n<ul>\n<li>0 &lt; N &lt; 10 , </li>\n<li>0 &lt; B<sub>1</sub> &lt; B<sub>2</sub> &lt; ... &lt; B<sub>N</sub> &lt; 100 , </li>\n<li>0 &lt; H<sub>1</sub> &lt; 50 , 0 &lt; H<sub>2</sub> &lt; 50 , ..., 0 &lt; H<sub>N</sub> &lt; 50.</li>\n</ul>\n<p>M is the number of the faucets above the tank . F<sub>j</sub> and A<sub>j</sub> are the x-position (cm) and the amount of water flow (cm3/second) of the j-th faucet , where 1 &lt;= j &lt;= M .</p>\n<p>There is no faucet just above any boards . Namely, none of F<sub>j</sub> is equal to B<sub>i</sub>.</p>\n<p>You may assume the following .</p>\n<ul>\n<li>0 &lt; M &lt;10 , </li>\n<li>0 &lt; F<sub>1</sub> &lt; F<sub>2</sub> &lt; ... &lt; F<sub>M</sub> &lt; 100 ,</li>\n<li>0 &lt; A<sub>1</sub> &lt; 100, 0 &lt; A<sub>2</sub> &lt; 100, ... 0 &lt; A<sub>M</sub> &lt; 100.</li>\n</ul>\n<p>L is the number of observation time and location. P<sub>k</sub> is the x-position (cm) of the k-th observation point. T<sub>k</sub> is the k-th observation time in seconds from the beginning.</p>\n<p>None of P<sub>k</sub> is equal to B<sub>i</sub>.</p>\n<p>You may assume the following .</p>\n<ul>\n<li>0 &lt; L &lt; 10 , </li>\n<li>0 &lt; P<sub>1</sub> &lt; 100, 0 &lt; P<sub>2</sub> &lt; 100, ..., 0 &lt; P<sub>L</sub> &lt; 100 , </li>\n<li>0 &lt; T<sub>1</sub> &lt; 1000000, 0 &lt; T<sub>2</sub> &lt; 1000000, ... , 0 &lt; T<sub>L</sub> &lt; 1000000.</li>\n</ul>",
  "output": "<p>For each data set, your program should output L lines each containing one real number which represents the height (cm) of the water level specified by the x-position P<sub>k</sub> at the time T<sub>k</sub>.</p>\n<p>Each answer may not have an error greater than 0.001. As long as this condition is satisfied, you may output any number of digits after the decimal point.</p>\n<p>After the water tank is filled to the brim, the water level at any P<sub>k</sub> is equal to the height of the tank, that is, 50 cm.</p>",
  "samples": [
    {
      "input": "2\n5\n15 40\n35 20\n50 45\n70 30\n80 10\n3\n20 3\n60 2\n65 2\n6\n40 4100\n25 7500\n10 18000\n90 7000\n25 15000\n25 22000\n5\n15 40\n35 20\n50 45\n70 30\n80 10\n2\n60 4\n75 1\n3\n60 6000\n75 6000\n85 6000\n",
      "output": "0.666667\n21.4286\n36.6667\n11.1111\n40.0\n50.0\n30.0\n13.3333\n13.3333\n"
    }
  ],
  "hint": null,
  "source": "ICPC, Regionals, Asia Pacific, Japan, Japan Domestic Contest, 2004 Japan Domestic Contest",
  "level": 0,
  "tags": [],
  "accepted_user_count": 0,
  "submission_count": null,
  "average_tries": 0
}