{
  "id": 26434,
  "title": "Happy Subarrays",
  "time_limit": "25 초 (추가 시간 없음)",
  "memory_limit": "1024 MB",
  "description": "<p>Let us define $F(B, L, R)$ as the sum of a subarray of an array $B$ bounded by indices $L$ and $R$ (both inclusive). Formally, $F(B, L, R) = B_L + B_{L+1} + \\cdots + B_R$.</p>\n<p>An array $C$ of length $K$ is called a happy array if all the prefix sums of $C$ are non-negative. Formally, the terms $F(C, 1, 1), F(C, 1, 2), \\dots, F(C, 1, K)$ are all non-negative.</p>\n<p>Given an array $\\mathbf{A}$ of $\\mathbf{N}$ integers, find the result of adding the sums of all the happy subarrays in the array $\\mathbf{A}$.</p>",
  "input": "<p>The first line of the input gives the number of test cases, $\\mathbf{T}$. $\\mathbf{T}$ test cases follow.</p>\n<p>Each test case begins with one line consisting an integer $\\mathbf{N}$ denoting the number of integers in the input array $\\mathbf{A}$. Then the next line contains $\\mathbf{N}$ integers $\\mathbf{A_1}, \\mathbf{A_2}, \\dots, \\mathbf{A_N}$ representing the integers in given input array $\\mathbf{A}$.</p>",
  "output": "<p>For each test case, output one line containing <code>Case #x: y</code>, where $x$ is the test case number (starting from 1) and $y$ is the result of adding the sums of all happy subarrays in the given input array $\\mathbf{A}$.</p>",
  "samples": [
    {
      "input": "2\n5\n1 -2 3 -2 4\n3\n1 0 3\n",
      "output": "Case #1: 14\nCase #2: 12\n"
    }
  ],
  "hint": null,
  "source": "Contest, Google, Kick Start, Google Kick Start 2022, Round G",
  "level": 17,
  "tags": [
    "data_structures",
    "prefix_sum",
    "stack"
  ],
  "accepted_user_count": 38,
  "submission_count": null,
  "average_tries": 1.3157999515533447
}