{
  "id": 26498,
  "title": "Snowflakes",
  "time_limit": "1 초",
  "memory_limit": "1024 MB",
  "description": "<p>Snowflakes can be symmetrical both vertically and horizontally. Snowflakes that aren’t symmetrical are useless. A snowflake is essentially a two dimensional array of features. A feature is a single digit between 0 and 9. Horizontal symmetry occurs if you flip the snowflake horizontally. It is still the same snowflake. Likewise, vertical symmetry is defined in the same way. A snowflake is “Beautiful” if its horizontally symmetrical, “Graceful” if its vertically symmetrical, and “Magnificent” if it is both. Otherwise it is “Useless”. For each snowflake, print what kind of snowflake it is.</p>",
  "input": "<p>The first line of data contains n, the number of inputs. Each input starts with a single integer k, k ≤ 20, denoting the dimension of the square snowflake. Then k lines follow with each line containing a string of length k denoting the digits in the snowflake.</p>",
  "output": "<p>For each input. print the type of snowflake.</p>",
  "samples": [
    {
      "input": "3\n3\n123\n321\n143\n2\n11\n11\n3\n121\n232\n343\n",
      "output": "Useless\nMagnificent\nGraceful\n"
    }
  ],
  "hint": null,
  "source": "School, PLU High School Programming Contest, PLU 2012, Advanced",
  "level": 5,
  "tags": [
    "implementation",
    "string"
  ],
  "accepted_user_count": 75,
  "submission_count": null,
  "average_tries": 1.3466999530792236
}