{
  "id": 16617,
  "title": "Far, Far Away",
  "time_limit": "2 초",
  "memory_limit": "512 MB",
  "description": "<p>As you know, the purpose of a journey is not to reach the destination but to make the trip. You want to make a trip with as many legs as possible. However, each leg of the trip costs some money and your budget is limited. Find the longest path!</p>",
  "input": "<p>The first line contains two integers n (1 ≤ n ≤ 100), which is the number of locations, and m (1 ≤ m ≤ 10<sup>9</sup>), which is the amount of available money.</p>\n<p>The next n lines describe the legs. Each of these lines contains n integers, where the j<sup>th</sup> integer of the i<sup>th</sup> line c<sub>ij</sub> is the cost of a leg from location i to location j (1 ≤ c<sub>ij</sub> ≤ 10<sup>9</sup> for each 1 ≤ i, j ≤ n). Your trip must start at location 1 and may end at any location.</p>",
  "output": "<p>Display the maximum number of legs a trip from location 1 can have such that the sum of the costs of its legs is at most m. A trip may repeatedly visit the same location (including start and destination) and repeatedly use the same leg (paying its cost multiple times).</p>",
  "samples": [
    {
      "input": "2 7\n3 2\n1 3\n",
      "output": "4\n"
    },
    {
      "input": "3 9\n2 5 4\n1 2 1\n1 1 2\n",
      "output": "6\n"
    },
    {
      "input": "2 1\n2 2\n1 1\n",
      "output": "0\n"
    },
    {
      "input": "2 3\n1 10\n10 10\n",
      "output": "3\n"
    }
  ],
  "hint": null,
  "source": "ICPC, Regionals, South Pacific, South Pacific Region, 2018 ACM South Pacific Programming Contest",
  "level": 19,
  "tags": [
    "dp",
    "data_structures",
    "graphs",
    "shortest_path",
    "parametric_search",
    "sparse_table",
    "floyd_warshall"
  ],
  "accepted_user_count": 17,
  "submission_count": null,
  "average_tries": 1.3529000282287598
}
