{
  "id": 5523,
  "title": "경기 결과",
  "time_limit": "1 초",
  "memory_limit": "256 MB",
  "description": "<p>A와 B가 게임을 한다. 게임은 N번의 라운드로 이루어져 있다. 각 라운드에서는, 더 많은 점수를 얻은 사람이 그 라운드의 승자가 된다. 즉, A의 점수가 B의 점수보다 크면 i번째 라운드는 A의 승리이며, B의 점수가 A의 점수보다 크면 i번째 라운드는 B의 승리이다. 무승부인 경우에는 아무도 승리하지 않는다.</p>\r\n\r\n<p>N번의 라운드에서의 A와 B의 점수가 주어졌을 때, A가 이긴 횟수와, B가 이긴 횟수를 출력하는 프로그램을 만들어라.</p>\r\n",
  "input": "<p>첫째 줄에는 정수 N(1 &le; N &le; 1,000,000)이 주어진다.</p>\r\n\r\n<p>둘째 줄부터는 정수 A<sub>i</sub>, B<sub>i</sub>&nbsp;(0 &le; A<sub>i</sub>, B<sub>i</sub>&nbsp;&le; 100)가 공백을 사이에 두고 차례대로 주어진다.</p>\r\n",
  "output": "<p>첫째 줄에 A가 이긴 횟수와 B가 이긴 횟수를 차례대로 출력하라.</p>\r\n",
  "samples": [
    {
      "input": "4\n100 0\n5 6\n40 50\n74 75\n",
      "output": "1 3\n"
    },
    {
      "input": "5\n20 20\n3 95\n60 59\n40 40\n20 19\n",
      "output": "2 1\n"
    }
  ],
  "hint": null,
  "source": ", Olympiad, Japanese Olympiad in Informatics, JOI 2012/2013 연습 세션, Olympiad, Japanese Olympiad in Informatics, JOI 2013/2014 연습 세션, baekjoon, onjo0127",
  "level": 3,
  "tags": ["implementation"],
  "accepted_user_count": 4278,
  "submission_count": null,
  "average_tries": 1.4306000471115112
}
