{
  "id": 18403,
  "title": "KABISA",
  "time_limit": "2 초",
  "memory_limit": "512 MB",
  "description": "<p>Many years ago, people were struggling with 6 hours extra that every year has. They decided to do calculate the 6 hours and keep every year as 365 days. The direct consequence of that calculation happened to the starting point of the new year. For example, they had a new year in winter, summer, fall, or spring. To fix the new years’ time, they decided to add extra day after every 4 years and they called it a leap year and keep the other 3 years 365 days. Your job is to write a program to find what are leap years in the given years.</p>",
  "input": "<p>First line contains the number of test cases (T): 1 ≤ T ≤ 10</p>\n<p>Second line indicates the list of given years Y, separated by commas (\",\"). 1 ≤ Y ≤ 2020</p>",
  "output": "<p>The list of leap years separated by space.</p>",
  "samples": [
    {
      "input": "1\n2, 1, 8, 6, 10, 12\n",
      "output": "8 12\n"
    }
  ],
  "hint": null,
  "source": "ICPC, Regionals, Asia West Continent, Afghanistan, ICPC Asia Kabul Regional Contest 2019",
  "level": 4,
  "tags": [
    "math",
    "implementation",
    "string",
    "arithmetic",
    "parsing"
  ],
  "accepted_user_count": 136,
  "submission_count": null,
  "average_tries": 1.5293999910354614
}