[{"input": "3\n2 1\n1 2 3 3\n4 5\n3 4 2 1\n2 3 3 3\n4 2 2 4\n1 2 3 5\n2 3 1 4\n5 6\n3 4 2 1\n4 5 1 4\n2 3 1 1\n1 2 1 4\n5 2 6 1\n2 5 1 5\n", "output": "Game #1: Suckzoo ends game in time 9, earning 9 garnet(s).\nGame #2: Suckzoo ends game in time 6, earning 10 garnet(s).\nGame #3: Suckzoo ends game in time 4, earning 19 garnet(s).\n"}, {"input": "3\n7 6\n1 2 4 3\n4 5 5 5\n3 4 2 5\n5 6 2 5\n6 7 2 2\n2 3 3 2\n3 2\n2 3 2 4\n1 2 2 2\n8 9\n6 7 2 2\n1 2 1 5\n3 4 3 5\n7 8 5 5\n8 5 4 7\n4 5 5 5\n5 6 1 2\n3 5 1 2\n2 3 5 5\n", "output": "Game #1: Suckzoo ends game in time 22, earning 32 garnet(s).\nGame #2: Suckzoo ends game in time 8, earning 14 garnet(s).\nGame #3: Suckzoo ends game in time 13, earning 29 garnet(s).\n"}, {"input": "4\n3 3\n1 2 1 4\n3 1 1 4\n2 3 3 5\n7 7\n3 4 3 5\n1 2 1 3\n4 5 2 4\n2 3 2 5\n5 6 4 1\n1 3 2 2\n6 7 3 2\n4 4\n3 4 1 5\n1 2 5 5\n2 3 3 2\n2 1 2 6\n7 8\n1 2 5 1\n2 3 2 3\n3 4 1 4\n6 7 5 2\n5 6 2 5\n4 2 6 10\n4 5 1 1\n5 4 6 10\n", "output": "Game #1: Suckzoo ends game in time 3, earning 12 garnet(s).\nGame #2: Suckzoo ends game in time 15, earning 20 garnet(s).\nGame #3: Suckzoo ends game in time 8, earning 23 garnet(s).\nGame #4: Suckzoo ends game in time 18, earning 24 garnet(s).\n"}, {"input": "3\n8 8\n6 7 2 3\n3 4 5 2\n1 2 4 2\n2 6 2 8\n2 3 1 4\n5 6 5 1\n4 5 4 5\n7 8 4 4\n7 7\n3 4 1 1\n1 2 1 3\n5 6 2 4\n2 3 5 3\n6 7 3 5\n4 5 2 2\n7 6 3 9\n3 2\n1 2 2 1\n2 3 1 3\n", "output": "Game #1: Suckzoo ends game in time 14, earning 25 garnet(s).\nGame #2: Suckzoo ends game in time 14, earning 22 garnet(s).\nGame #3: Suckzoo ends game in time 5, earning 10 garnet(s).\n"}, {"input": "4\n3 2\n1 2 5 4\n2 3 3 5\n2 1\n1 2 3 2\n3 2\n1 2 4 3\n2 3 4 2\n2 1\n1 2 5 2\n", "output": "Game #1: Suckzoo ends game in time 14, earning 19 garnet(s).\nGame #2: Suckzoo ends game in time 9, earning 6 garnet(s).\nGame #3: Suckzoo ends game in time 16, earning 11 garnet(s).\nGame #4: Suckzoo ends game in time 15, earning 6 garnet(s).\n"}, {"input": "4\n5 5\n3 4 4 4\n4 5 5 3\n2 3 1 2\n1 2 3 4\n3 4 1 5\n3 2\n2 3 5 5\n1 2 2 1\n6 6\n1 2 1 5\n4 5 5 3\n2 3 2 4\n5 6 5 5\n4 2 1 1\n3 4 2 4\n6 7\n2 5 2 10\n5 1 3 8\n1 2 1 1\n4 5 1 2\n3 4 4 3\n2 3 1 1\n5 6 4 4\n", "output": "Game #1: Suckzoo ends game in time 12, earning 24 garnet(s).\nGame #2: Suckzoo ends game in time 11, earning 8 garnet(s).\nGame #3: Suckzoo ends game in time 14, earning 24 garnet(s).\nGame #4: Suckzoo ends game in time 4611686018427387903, earning 4611686018427387903 garnet(s).\n"}, {"input": "5\n4 3\n3 4 2 1\n2 3 3 1\n1 2 3 2\n2 1\n1 2 2 5\n3 3\n1 2 3 3\n2 3 1 2\n1 3 5 1\n3 3\n1 2 2 1\n3 2 5 1\n2 3 2 2\n4 3\n1 2 5 4\n3 4 4 3\n2 3 5 1\n", "output": "Game #1: Suckzoo ends game in time 12, earning 6 garnet(s).\nGame #2: Suckzoo ends game in time 6, earning 15 garnet(s).\nGame #3: Suckzoo ends game in time 5, earning 1 garnet(s).\nGame #4: Suckzoo ends game in time 7, earning 2 garnet(s).\nGame #5: Suckzoo ends game in time 22, earning 14 garnet(s).\n"}, {"input": "3\n7 9\n1 2 1 3\n6 7 4 1\n5 6 2 5\n6 7 5 4\n4 5 5 4\n2 7 1 9\n3 4 3 4\n5 1 6 8\n2 3 2 4\n3 2\n2 3 5 3\n1 2 2 5\n6 7\n3 5 1 7\n1 2 5 4\n3 4 2 3\n5 6 2 3\n1 4 1 9\n4 5 5 5\n2 3 1 2\n", "output": "Game #1: Suckzoo ends game in time 4, earning 30 garnet(s).\nGame #2: Suckzoo ends game in time 11, earning 18 garnet(s).\nGame #3: Suckzoo ends game in time 8, earning 40 garnet(s).\n"}, {"input": "5\n5 4\n2 3 1 1\n3 4 5 2\n4 5 1 5\n1 2 2 1\n2 1\n1 2 4 3\n6 5\n1 2 2 2\n5 6 5 3\n4 5 2 1\n3 4 5 5\n2 3 3 5\n5 4\n4 5 1 3\n2 3 5 3\n1 2 1 1\n3 4 1 5\n5 6\n1 2 1 2\n2 3 4 10\n2 3 2 4\n3 4 5 3\n3 4 5 6\n4 5 5 2\n", "output": "Game #1: Suckzoo ends game in time 11, earning 19 garnet(s).\nGame #2: Suckzoo ends game in time 12, earning 9 garnet(s).\nGame #3: Suckzoo ends game in time 21, earning 20 garnet(s).\nGame #4: Suckzoo ends game in time 10, earning 22 garnet(s).\nGame #5: Suckzoo ends game in time 4611686018427387903, earning 4611686018427387903 garnet(s).\n"}, {"input": "4\n3 3\n2 3 1 2\n1 2 1 1\n2 3 1 2\n3 3\n2 1 1 9\n2 3 2 5\n1 2 2 1\n5 6\n4 5 5 5\n1 2 1 5\n3 4 3 5\n5 1 2 8\n1 5 2 4\n2 3 4 2\n4 5\n1 2 2 2\n3 2 6 4\n3 4 4 10\n2 3 5 2\n3 4 2 5\n", "output": "Game #1: Suckzoo ends game in time 2, earning 3 garnet(s).\nGame #2: Suckzoo ends game in time 4, earning 6 garnet(s).\nGame #3: Suckzoo ends game in time 2, earning 8 garnet(s).\nGame #4: Suckzoo ends game in time 11, earning 14 garnet(s).\n"}, {"input": "5\n3 3\n2 3 1 10\n1 2 1 4\n2 3 5 4\n5 7\n1 2 1 3\n2 3 2 4\n1 4 2 7\n4 5 5 2\n5 4 2 4\n3 4 1 1\n1 2 1 3\n5 6\n4 5 1 4\n3 4 6 4\n4 5 2 2\n3 4 5 4\n1 2 4 1\n2 3 5 5\n7 8\n6 7 4 8\n1 2 1 2\n6 7 1 5\n5 6 5 1\n2 3 5 3\n3 4 1 7\n3 4 4 2\n4 5 3 2\n3 2\n1 2 1 1\n2 3 4 1\n", "output": "Game #1: Suckzoo ends game in time 4, earning 34 garnet(s).\nGame #2: Suckzoo ends game in time 6, earning 17 garnet(s).\nGame #3: Suckzoo ends game in time 16, earning 12 garnet(s).\nGame #4: Suckzoo ends game in time 18, earning 34 garnet(s).\nGame #5: Suckzoo ends game in time 7, earning 4 garnet(s).\n"}, {"input": "4\n5 6\n4 5 2 3\n3 5 2 6\n3 4 1 3\n2 4 1 8\n2 3 2 1\n1 2 4 2\n8 7\n3 4 1 5\n4 5 5 2\n6 7 4 1\n5 6 1 2\n7 8 1 4\n1 2 1 1\n2 3 2 5\n6 8\n5 3 1 4\n5 6 1 3\n3 4 2 1\n2 3 2 4\n1 2 1 5\n5 6 1 1\n4 5 5 5\n5 6 3 2\n7 7\n4 5 2 5\n5 6 3 1\n1 2 1 5\n2 3 1 3\n4 3 2 6\n6 7 5 3\n3 4 1 2\n", "output": "Game #1: Suckzoo ends game in time 8, earning 19 garnet(s).\nGame #2: Suckzoo ends game in time 17, earning 30 garnet(s).\nGame #3: Suckzoo ends game in time 5, earning 16 garnet(s).\nGame #4: Suckzoo ends game in time 19, earning 21 garnet(s).\n"}, {"input": "3\n3 2\n2 3 1 1\n1 2 5 1\n3 2\n2 3 1 2\n1 2 4 2\n3 2\n2 3 4 4\n1 2 1 2\n", "output": "Game #1: Suckzoo ends game in time 8, earning 4 garnet(s).\nGame #2: Suckzoo ends game in time 7, earning 8 garnet(s).\nGame #3: Suckzoo ends game in time 7, earning 10 garnet(s).\n"}, {"input": "5\n5 7\n4 5 2 4\n2 3 4 2\n3 4 3 2\n1 2 2 3\n1 5 2 9\n5 1 1 5\n3 4 4 3\n2 1\n1 2 4 1\n3 2\n1 2 1 3\n2 3 4 4\n6 8\n1 2 5 1\n2 3 4 2\n3 4 3 1\n1 4 3 6\n5 4 2 10\n6 1 3 7\n5 6 1 5\n4 5 2 1\n4 3\n2 3 5 4\n3 4 2 2\n1 2 1 2\n", "output": "Game #1: Suckzoo ends game in time 2, earning 9 garnet(s).\nGame #2: Suckzoo ends game in time 12, earning 3 garnet(s).\nGame #3: Suckzoo ends game in time 7, earning 13 garnet(s).\nGame #4: Suckzoo ends game in time 5, earning 17 garnet(s).\nGame #5: Suckzoo ends game in time 10, earning 12 garnet(s).\n"}, {"input": "3\n7 8\n1 2 3 5\n6 7 5 1\n4 5 3 5\n5 6 5 4\n3 7 1 7\n2 3 1 4\n3 4 2 2\n1 3 2 2\n2 1\n1 2 2 2\n8 10\n7 8 2 2\n1 2 1 5\n2 3 3 4\n5 6 5 4\n4 5 4 6\n3 4 2 5\n6 7 4 4\n4 5 2 1\n5 6 1 4\n1 2 2 1\n", "output": "Game #1: Suckzoo ends game in time 5, earning 23 garnet(s).\nGame #2: Suckzoo ends game in time 6, earning 6 garnet(s).\nGame #3: Suckzoo ends game in time 16, earning 21 garnet(s).\n"}, {"input": "4\n5 7\n2 3 3 2\n2 3 4 3\n4 5 3 2\n4 5 5 2\n1 2 2 2\n3 2 4 2\n3 4 5 4\n7 8\n5 6 3 5\n2 3 2 3\n1 2 3 3\n6 4 1 4\n3 4 4 3\n6 7 1 3\n2 5 1 2\n4 5 3 3\n6 6\n1 2 4 5\n2 3 4 1\n5 6 4 1\n6 2 3 8\n3 4 3 4\n4 5 4 2\n4 3\n3 4 3 5\n2 3 4 3\n1 2 3 4\n", "output": "Game #1: Suckzoo ends game in time 14, earning 11 garnet(s).\nGame #2: Suckzoo ends game in time 9, earning 15 garnet(s).\nGame #3: Suckzoo ends game in time 13, earning 29 garnet(s).\nGame #4: Suckzoo ends game in time 16, earning 22 garnet(s).\n"}, {"input": "4\n2 1\n1 2 4 2\n6 6\n4 5 1 5\n3 4 1 2\n5 6 4 3\n2 3 1 4\n1 2 2 4\n6 2 2 9\n7 9\n5 6 3 5\n4 5 1 4\n3 4 4 3\n6 7 1 2\n7 1 2 5\n1 2 5 1\n7 1 2 2\n5 3 2 4\n2 3 1 3\n2 1\n1 2 5 5\n", "output": "Game #1: Suckzoo ends game in time 12, earning 6 garnet(s).\nGame #2: Suckzoo ends game in time 6, earning 21 garnet(s).\nGame #3: Suckzoo ends game in time 2, earning 5 garnet(s).\nGame #4: Suckzoo ends game in time 15, earning 15 garnet(s).\n"}, {"input": "5\n7 7\n2 3 1 3\n4 5 3 2\n6 7 3 4\n5 6 1 4\n1 2 5 3\n1 7 2 9\n3 4 3 5\n7 9\n6 7 3 3\n2 6 1 4\n3 4 1 2\n3 6 3 1\n3 5 1 3\n4 5 1 2\n1 2 5 2\n2 3 2 3\n5 6 2 1\n2 1\n1 2 5 4\n6 6\n5 6 5 4\n2 3 5 1\n6 3 3 7\n3 4 4 4\n4 5 1 1\n1 2 2 2\n6 5\n2 3 4 3\n3 4 2 4\n4 5 1 4\n1 2 5 2\n5 6 3 2\n", "output": "Game #1: Suckzoo ends game in time 6, earning 27 garnet(s).\nGame #2: Suckzoo ends game in time 11, earning 17 garnet(s).\nGame #3: Suckzoo ends game in time 15, earning 12 garnet(s).\nGame #4: Suckzoo ends game in time 14, earning 14 garnet(s).\nGame #5: Suckzoo ends game in time 17, earning 23 garnet(s).\n"}, {"input": "4\n2 1\n1 2 4 2\n7 8\n3 4 3 3\n5 6 3 3\n2 3 4 5\n6 7 5 4\n1 2 3 4\n3 4 1 3\n4 5 2 3\n4 7 2 5\n4 5\n2 3 2 3\n1 2 5 3\n3 4 6 7\n1 2 4 3\n3 4 2 4\n5 5\n3 4 3 4\n4 5 5 3\n2 3 4 4\n2 3 1 1\n1 2 2 5\n", "output": "Game #1: Suckzoo ends game in time 12, earning 6 garnet(s).\nGame #2: Suckzoo ends game in time 12, earning 23 garnet(s).\nGame #3: Suckzoo ends game in time 12, earning 18 garnet(s).\nGame #4: Suckzoo ends game in time 13, earning 15 garnet(s).\n"}, {"input": "5\n7 8\n6 7 5 3\n5 6 1 1\n2 3 5 4\n4 5 4 5\n4 3 2 4\n3 7 1 6\n1 2 1 5\n3 4 4 5\n7 7\n4 5 5 4\n6 4 1 3\n5 6 5 2\n2 3 5 2\n1 2 4 3\n6 7 4 3\n3 4 3 3\n8 10\n4 5 5 3\n4 3 2 5\n6 7 2 5\n2 3 2 2\n3 4 5 3\n7 8 1 5\n3 1 3 4\n7 8 2 3\n1 2 1 5\n5 6 3 2\n4 3\n3 4 3 4\n1 2 1 5\n2 3 1 5\n4 4\n2 3 3 4\n1 2 2 3\n3 1 3 2\n3 4 3 5\n", "output": "Game #1: Suckzoo ends game in time 9, earning 27 garnet(s).\nGame #2: Suckzoo ends game in time 19, earning 20 garnet(s).\nGame #3: Suckzoo ends game in time 17, earning 25 garnet(s).\nGame #4: Suckzoo ends game in time 7, earning 24 garnet(s).\nGame #5: Suckzoo ends game in time 8, earning 12 garnet(s).\n"}, {"input": "4\n5 7\n1 2 4 4\n4 5 3 2\n1 2 4 4\n2 3 3 1\n5 1 4 8\n3 4 3 3\n2 5 6 6\n2 1\n1 2 2 5\n6 8\n1 2 2 4\n2 3 4 5\n5 6 3 5\n3 5 1 4\n5 6 2 5\n3 4 3 4\n4 5 3 4\n6 3 2 9\n5 4\n4 5 5 2\n2 3 5 3\n1 2 1 3\n3 4 3 2\n", "output": "Game #1: Suckzoo ends game in time 10, earning 12 garnet(s).\nGame #2: Suckzoo ends game in time 6, earning 15 garnet(s).\nGame #3: Suckzoo ends game in time 9, earning 18 garnet(s).\nGame #4: Suckzoo ends game in time 16, earning 16 garnet(s).\n"}, {"input": "4\n4 6\n1 2 1 2\n1 2 4 2\n1 2 6 5\n3 4 2 1\n4 1 5 3\n2 3 2 4\n2 1\n1 2 2 5\n8 8\n3 4 4 3\n5 6 5 2\n1 2 1 1\n8 1 3 9\n2 3 3 1\n6 7 1 3\n7 8 5 1\n4 5 1 1\n7 6\n4 5 5 4\n5 6 5 1\n6 7 3 2\n3 4 4 3\n2 3 4 2\n1 2 2 1\n", "output": "Game #1: Suckzoo ends game in time 5, earning 7 garnet(s).\nGame #2: Suckzoo ends game in time 6, earning 15 garnet(s).\nGame #3: Suckzoo ends game in time 5, earning 11 garnet(s).\nGame #4: Suckzoo ends game in time 27, earning 15 garnet(s).\n"}, {"input": "5\n3 3\n1 2 2 5\n2 3 5 3\n1 2 6 10\n5 6\n2 3 1 2\n4 1 4 4\n1 2 1 5\n3 4 3 5\n4 5 5 4\n1 2 2 10\n6 6\n4 5 3 5\n1 2 1 2\n3 4 2 3\n2 3 1 1\n1 6 2 1\n5 6 4 2\n4 5\n3 4 2 1\n3 4 5 8\n2 3 1 2\n2 4 6 10\n1 2 1 4\n3 2\n1 2 3 3\n2 3 3 1\n", "output": "Game #1: Suckzoo ends game in time 11, earning 18 garnet(s).\nGame #2: Suckzoo ends game in time 10, earning 16 garnet(s).\nGame #3: Suckzoo ends game in time 4, earning 5 garnet(s).\nGame #4: Suckzoo ends game in time 6, earning 15 garnet(s).\nGame #5: Suckzoo ends game in time 12, earning 10 garnet(s).\n"}, {"input": "4\n5 6\n2 3 3 5\n3 4 5 1\n1 5 2 1\n4 5 4 4\n1 2 5 1\n3 4 3 10\n7 9\n1 2 4 2\n5 6 4 4\n2 5 4 9\n4 5 4 3\n2 3 3 1\n5 7 4 2\n3 6 5 6\n6 7 1 4\n3 4 5 2\n7 6\n2 3 4 5\n1 2 4 1\n4 5 2 5\n3 4 5 2\n5 6 2 1\n6 7 1 1\n3 2\n1 2 3 5\n2 3 4 2\n", "output": "Game #1: Suckzoo ends game in time 6, earning 3 garnet(s).\nGame #2: Suckzoo ends game in time 13, earning 19 garnet(s).\nGame #3: Suckzoo ends game in time 20, earning 17 garnet(s).\nGame #4: Suckzoo ends game in time 13, earning 17 garnet(s).\n"}, {"input": "5\n4 4\n4 1 1 3\n3 4 3 5\n1 2 1 1\n2 3 4 2\n8 8\n2 1 2 1\n3 4 2 3\n5 6 3 1\n6 7 5 5\n2 3 5 1\n7 8 4 4\n1 2 4 5\n4 5 3 1\n5 4\n3 4 3 1\n1 2 3 4\n2 3 1 5\n4 5 2 2\n4 5\n2 3 1 5\n1 2 3 3\n3 4 1 1\n4 1 6 8\n3 4 3 1\n7 8\n3 4 1 2\n4 5 2 4\n3 7 6 5\n2 3 1 2\n1 2 1 4\n5 6 2 1\n6 7 3 3\n1 6 6 5\n", "output": "Game #1: Suckzoo ends game in time 3, earning 9 garnet(s).\nGame #2: Suckzoo ends game in time 26, earning 20 garnet(s).\nGame #3: Suckzoo ends game in time 11, earning 22 garnet(s).\nGame #4: Suckzoo ends game in time 6, earning 8 garnet(s).\nGame #5: Suckzoo ends game in time 9, earning 8 garnet(s).\n"}, {"input": "4\n2 1\n1 2 4 3\n6 7\n3 4 3 2\n1 6 2 6\n1 2 2 5\n2 3 3 1\n5 6 1 2\n3 1 1 2\n4 5 3 3\n5 5\n3 4 5 5\n2 3 2 5\n4 5 1 5\n2 3 4 1\n1 2 3 2\n6 5\n4 5 4 1\n3 4 1 5\n1 2 2 5\n5 6 1 1\n2 3 3 5\n", "output": "Game #1: Suckzoo ends game in time 12, earning 9 garnet(s).\nGame #2: Suckzoo ends game in time 4, earning 10 garnet(s).\nGame #3: Suckzoo ends game in time 13, earning 27 garnet(s).\nGame #4: Suckzoo ends game in time 13, earning 27 garnet(s).\n"}, {"input": "3\n8 10\n6 7 2 3\n7 8 1 3\n8 4 2 10\n5 6 5 2\n4 1 2 4\n3 4 1 5\n1 2 4 5\n4 5 4 1\n6 8 1 2\n2 3 1 4\n2 1\n1 2 5 5\n8 8\n7 8 1 2\n5 6 2 1\n4 5 4 5\n1 2 3 1\n7 6 3 7\n2 3 2 2\n3 4 1 4\n6 7 4 3\n", "output": "Game #1: Suckzoo ends game in time 6, earning 24 garnet(s).\nGame #2: Suckzoo ends game in time 15, earning 15 garnet(s).\nGame #3: Suckzoo ends game in time 17, earning 18 garnet(s).\n"}, {"input": "4\n6 7\n5 6 4 4\n3 4 2 4\n2 3 3 1\n1 2 3 3\n4 5 4 2\n5 3 2 7\n6 5 1 9\n4 4\n2 3 4 3\n1 2 3 1\n2 4 6 9\n3 4 3 1\n8 9\n6 7 5 2\n1 2 5 1\n7 8 5 1\n5 6 5 2\n3 2 4 1\n2 3 1 5\n4 5 2 1\n4 5 3 10\n3 4 1 2\n8 8\n6 7 5 1\n4 5 3 5\n5 6 1 4\n5 3 4 5\n3 4 2 1\n7 8 2 4\n1 2 3 2\n2 3 2 2\n", "output": "Game #1: Suckzoo ends game in time 11, earning 38 garnet(s).\nGame #2: Suckzoo ends game in time 10, earning 5 garnet(s).\nGame #3: Suckzoo ends game in time 25, earning 23 garnet(s).\nGame #4: Suckzoo ends game in time 18, earning 19 garnet(s).\n"}, {"input": "3\n2 1\n1 2 3 4\n4 4\n3 4 2 1\n1 2 3 5\n2 3 4 3\n1 4 1 10\n6 8\n6 4 5 6\n2 3 5 4\n5 6 2 4\n3 4 3 1\n6 5 5 10\n1 2 1 1\n4 6 6 1\n4 5 5 2\n", "output": "Game #1: Suckzoo ends game in time 9, earning 12 garnet(s).\nGame #2: Suckzoo ends game in time 3, earning 30 garnet(s).\nGame #3: Suckzoo ends game in time 15, earning 7 garnet(s).\n"}, {"input": "5\n7 8\n5 1 1 2\n1 2 3 1\n2 3 3 2\n5 7 1 1\n4 5 5 3\n3 4 2 5\n6 7 2 3\n5 6 2 5\n4 5\n2 3 4 3\n2 1 6 10\n1 2 1 2\n3 4 1 3\n2 4 6 2\n2 1\n1 2 3 2\n4 5\n1 2 2 4\n1 2 2 3\n2 3 1 2\n3 2 2 1\n3 4 2 3\n8 9\n1 2 2 3\n4 5 5 2\n7 8 2 5\n5 6 4 5\n6 7 5 4\n2 3 5 3\n7 8 2 4\n3 4 3 5\n1 2 5 2\n", "output": "Game #1: Suckzoo ends game in time 4, earning 7 garnet(s).\nGame #2: Suckzoo ends game in time 7, earning 4 garnet(s).\nGame #3: Suckzoo ends game in time 9, earning 6 garnet(s).\nGame #4: Suckzoo ends game in time 5, earning 9 garnet(s).\nGame #5: Suckzoo ends game in time 26, earning 27 garnet(s).\n"}, {"input": "3\n2 1\n1 2 2 3\n4 5\n2 3 1 9\n4 1 6 9\n1 2 3 5\n3 4 4 2\n2 3 1 2\n3 2\n1 2 4 1\n2 3 5 3\n", "output": "Game #1: Suckzoo ends game in time 6, earning 9 garnet(s).\nGame #2: Suckzoo ends game in time 8, earning 16 garnet(s).\nGame #3: Suckzoo ends game in time 17, earning 6 garnet(s).\n"}, {"input": "3\n7 9\n6 7 2 3\n2 5 5 9\n4 2 6 4\n4 5 5 3\n1 2 1 5\n4 7 5 10\n5 6 1 3\n3 4 5 1\n2 3 5 2\n2 1\n1 2 3 4\n2 1\n1 2 2 5\n", "output": "Game #1: Suckzoo ends game in time 11, earning 30 garnet(s).\nGame #2: Suckzoo ends game in time 9, earning 12 garnet(s).\nGame #3: Suckzoo ends game in time 6, earning 15 garnet(s).\n"}, {"input": "4\n6 5\n3 4 3 4\n5 6 5 3\n1 2 5 4\n4 5 4 5\n2 3 1 5\n8 9\n6 1 4 10\n5 4 3 2\n1 2 2 2\n4 5 1 1\n2 3 3 3\n7 8 2 4\n6 7 5 3\n5 6 3 2\n3 4 4 4\n8 10\n2 3 3 4\n4 7 5 7\n3 4 5 2\n6 7 3 4\n4 5 1 2\n6 4 5 7\n2 4 3 7\n7 8 4 1\n1 2 1 3\n5 6 1 3\n2 1\n1 2 4 2\n", "output": "Game #1: Suckzoo ends game in time 20, earning 31 garnet(s).\nGame #2: Suckzoo ends game in time 15, earning 25 garnet(s).\nGame #3: Suckzoo ends game in time 4611686018427387903, earning 4611686018427387903 garnet(s).\nGame #4: Suckzoo ends game in time 12, earning 6 garnet(s).\n"}, {"input": "3\n2 1\n1 2 1 3\n2 1\n1 2 1 5\n3 2\n1 2 5 4\n2 3 2 1\n", "output": "Game #1: Suckzoo ends game in time 3, earning 9 garnet(s).\nGame #2: Suckzoo ends game in time 3, earning 15 garnet(s).\nGame #3: Suckzoo ends game in time 11, earning 7 garnet(s).\n"}, {"input": "5\n4 3\n3 4 1 5\n2 3 4 4\n1 2 4 4\n2 1\n1 2 3 5\n3 3\n1 2 3 1\n3 2 2 4\n2 3 1 1\n6 6\n4 5 3 2\n3 4 4 3\n2 3 1 5\n5 2 2 4\n5 6 2 2\n1 2 2 4\n6 7\n5 6 2 3\n3 4 4 2\n3 4 4 8\n2 3 1 1\n4 5 5 3\n1 2 2 1\n5 6 5 3\n", "output": "Game #1: Suckzoo ends game in time 11, earning 23 garnet(s).\nGame #2: Suckzoo ends game in time 9, earning 15 garnet(s).\nGame #3: Suckzoo ends game in time 5, earning 5 garnet(s).\nGame #4: Suckzoo ends game in time 8, earning 20 garnet(s).\nGame #5: Suckzoo ends game in time 17, earning 16 garnet(s).\n"}, {"input": "4\n6 6\n1 2 4 2\n4 5 5 1\n1 4 1 9\n2 3 1 4\n5 6 4 3\n3 4 5 2\n4 3\n3 4 5 2\n1 2 4 5\n2 3 5 3\n4 5\n2 3 2 1\n3 4 1 1\n1 2 1 9\n1 2 4 3\n4 1 2 9\n2 1\n1 2 1 4\n", "output": "Game #1: Suckzoo ends game in time 12, earning 31 garnet(s).\nGame #2: Suckzoo ends game in time 22, earning 20 garnet(s).\nGame #3: Suckzoo ends game in time 4, earning 27 garnet(s).\nGame #4: Suckzoo ends game in time 3, earning 12 garnet(s).\n"}, {"input": "3\n4 3\n3 4 5 5\n1 2 2 3\n2 3 5 1\n7 9\n1 2 3 3\n3 7 6 7\n6 7 3 3\n5 6 2 4\n1 3 6 1\n2 3 3 1\n4 5 5 4\n7 3 3 9\n3 4 3 2\n8 8\n5 6 1 4\n2 3 1 1\n3 4 3 2\n6 7 2 1\n4 5 4 5\n4 5 6 2\n7 8 4 5\n1 2 4 5\n", "output": "Game #1: Suckzoo ends game in time 16, earning 15 garnet(s).\nGame #2: Suckzoo ends game in time 12, earning 11 garnet(s).\nGame #3: Suckzoo ends game in time 21, earning 31 garnet(s).\n"}, {"input": "4\n3 2\n1 2 5 3\n2 3 1 2\n2 1\n1 2 1 4\n5 7\n2 3 3 3\n1 2 5 3\n5 3 1 1\n2 3 5 5\n4 5 1 5\n3 4 3 4\n3 5 6 9\n2 1\n1 2 4 3\n", "output": "Game #1: Suckzoo ends game in time 8, earning 9 garnet(s).\nGame #2: Suckzoo ends game in time 3, earning 12 garnet(s).\nGame #3: Suckzoo ends game in time 11, earning 17 garnet(s).\nGame #4: Suckzoo ends game in time 12, earning 9 garnet(s).\n"}, {"input": "4\n5 4\n1 2 5 1\n4 5 5 3\n2 3 1 2\n3 4 3 1\n2 1\n1 2 5 1\n3 2\n2 3 1 3\n1 2 3 5\n5 7\n1 2 2 3\n2 3 5 4\n4 5 3 4\n4 5 2 1\n1 4 1 8\n4 3 1 10\n3 4 5 1\n", "output": "Game #1: Suckzoo ends game in time 16, earning 11 garnet(s).\nGame #2: Suckzoo ends game in time 15, earning 3 garnet(s).\nGame #3: Suckzoo ends game in time 6, earning 14 garnet(s).\nGame #4: Suckzoo ends game in time 4, earning 12 garnet(s).\n"}, {"input": "5\n3 3\n3 1 6 7\n1 2 1 4\n2 3 5 1\n4 3\n2 3 3 3\n1 2 1 5\n3 4 1 4\n8 8\n4 5 3 1\n7 2 5 8\n3 4 2 1\n5 6 3 3\n1 2 2 1\n2 3 5 2\n7 8 1 3\n6 7 3 2\n4 4\n3 4 4 4\n2 3 5 1\n1 2 4 2\n4 3 2 7\n8 8\n1 2 2 3\n4 5 1 4\n6 7 2 5\n2 3 2 3\n5 6 4 4\n7 8 5 5\n3 4 4 1\n8 2 2 5\n", "output": "Game #1: Suckzoo ends game in time 6, earning 7 garnet(s).\nGame #2: Suckzoo ends game in time 7, earning 22 garnet(s).\nGame #3: Suckzoo ends game in time 10, earning 18 garnet(s).\nGame #4: Suckzoo ends game in time 13, earning 7 garnet(s).\nGame #5: Suckzoo ends game in time 8, earning 18 garnet(s).\n"}, {"input": "4\n6 5\n2 3 5 1\n5 6 5 4\n1 2 1 4\n3 4 4 2\n4 5 1 1\n6 5\n4 5 5 4\n3 4 1 3\n5 6 2 4\n2 3 2 2\n1 2 3 2\n2 1\n1 2 2 4\n7 9\n2 3 2 3\n3 4 2 2\n1 2 4 2\n5 6 4 2\n1 6 2 4\n5 2 5 4\n6 7 1 1\n4 5 4 1\n1 2 2 7\n", "output": "Game #1: Suckzoo ends game in time 18, earning 20 garnet(s).\nGame #2: Suckzoo ends game in time 15, earning 21 garnet(s).\nGame #3: Suckzoo ends game in time 6, earning 12 garnet(s).\nGame #4: Suckzoo ends game in time 5, earning 7 garnet(s).\n"}, {"input": "3\n4 4\n2 3 4 5\n1 2 5 1\n1 4 2 3\n3 4 2 5\n2 1\n1 2 1 1\n6 8\n5 6 1 3\n1 2 5 5\n4 5 4 3\n2 3 3 3\n4 5 1 4\n4 1 1 9\n3 4 4 3\n1 3 1 6\n", "output": "Game #1: Suckzoo ends game in time 6, earning 13 garnet(s).\nGame #2: Suckzoo ends game in time 3, earning 3 garnet(s).\nGame #3: Suckzoo ends game in time 5, earning 34 garnet(s).\n"}, {"input": "4\n3 2\n2 3 5 3\n1 2 5 3\n8 9\n7 8 1 3\n2 3 3 5\n6 7 3 2\n2 8 2 3\n3 4 4 1\n4 5 4 1\n2 8 1 8\n5 6 4 1\n1 2 1 1\n2 1\n1 2 5 4\n4 4\n1 2 3 3\n4 2 1 3\n2 3 2 1\n3 4 5 5\n", "output": "Game #1: Suckzoo ends game in time 20, earning 12 garnet(s).\nGame #2: Suckzoo ends game in time 3, earning 4 garnet(s).\nGame #3: Suckzoo ends game in time 15, earning 12 garnet(s).\nGame #4: Suckzoo ends game in time 6, earning 12 garnet(s).\n"}, {"input": "3\n8 10\n1 2 4 5\n6 4 1 1\n7 2 2 3\n6 7 5 1\n7 8 3 4\n2 3 4 5\n4 5 1 3\n5 6 1 1\n3 4 5 5\n1 5 2 2\n2 1\n1 2 4 5\n6 8\n5 6 2 5\n2 6 4 3\n3 4 1 4\n5 1 5 3\n2 3 2 5\n6 5 4 4\n4 5 1 2\n1 2 3 3\n", "output": "Game #1: Suckzoo ends game in time 4611686018427387903, earning 4611686018427387903 garnet(s).\nGame #2: Suckzoo ends game in time 12, earning 15 garnet(s).\nGame #3: Suckzoo ends game in time 7, earning 8 garnet(s).\n"}, {"input": "5\n7 9\n2 5 6 8\n6 7 4 2\n4 3 1 5\n5 6 4 2\n3 4 3 4\n2 3 2 5\n3 4 4 1\n4 5 1 5\n1 2 2 3\n8 7\n3 4 2 4\n5 6 3 3\n2 3 3 4\n6 7 4 4\n7 8 5 2\n1 2 3 3\n4 5 3 4\n8 8\n7 8 3 1\n5 6 4 2\n3 4 4 4\n6 7 3 3\n2 3 3 3\n7 3 2 5\n4 5 5 4\n1 2 5 2\n4 5\n2 3 2 3\n1 2 1 4\n2 3 5 9\n1 2 4 2\n3 4 2 4\n4 4\n1 2 3 5\n2 3 1 2\n1 3 6 6\n3 4 1 1\n", "output": "Game #1: Suckzoo ends game in time 16, earning 32 garnet(s).\nGame #2: Suckzoo ends game in time 27, earning 32 garnet(s).\nGame #3: Suckzoo ends game in time 17, earning 21 garnet(s).\nGame #4: Suckzoo ends game in time 7, earning 19 garnet(s).\nGame #5: Suckzoo ends game in time 7, earning 12 garnet(s).\n"}, {"input": "4\n3 2\n2 3 5 1\n1 2 1 2\n7 8\n3 4 5 4\n5 6 6 2\n4 5 1 1\n2 3 3 2\n1 2 1 1\n5 6 3 1\n6 7 3 1\n7 1 1 3\n5 7\n4 1 4 9\n4 5 2 3\n2 3 1 2\n2 4 6 9\n3 4 4 3\n5 3 6 6\n1 2 2 2\n6 8\n3 4 1 2\n1 2 3 5\n6 2 1 9\n4 5 4 2\n2 3 2 2\n2 4 5 8\n5 6 3 3\n2 1 4 8\n", "output": "Game #1: Suckzoo ends game in time 8, earning 7 garnet(s).\nGame #2: Suckzoo ends game in time 3, earning 9 garnet(s).\nGame #3: Suckzoo ends game in time 9, earning 10 garnet(s).\nGame #4: Suckzoo ends game in time 5, earning 17 garnet(s).\n"}, {"input": "5\n8 8\n3 4 1 4\n7 8 5 3\n2 3 3 3\n5 6 5 1\n6 7 3 3\n4 3 2 2\n4 5 2 5\n1 2 5 5\n3 2\n1 2 2 5\n2 3 4 4\n4 5\n2 3 2 1\n3 4 2 2\n2 3 1 10\n3 1 2 7\n1 2 5 4\n5 4\n4 5 4 3\n2 3 2 5\n3 4 3 2\n1 2 2 3\n3 2\n1 2 5 2\n2 3 5 1\n", "output": "Game #1: Suckzoo ends game in time 25, earning 22 garnet(s).\nGame #2: Suckzoo ends game in time 10, earning 19 garnet(s).\nGame #3: Suckzoo ends game in time 6, earning 29 garnet(s).\nGame #4: Suckzoo ends game in time 15, earning 23 garnet(s).\nGame #5: Suckzoo ends game in time 20, earning 7 garnet(s).\n"}, {"input": "3\n6 6\n5 6 3 4\n2 3 5 1\n1 2 1 1\n4 5 1 2\n3 4 2 3\n3 1 6 3\n4 5\n2 3 2 8\n1 2 1 2\n2 3 2 4\n3 4 2 3\n1 2 2 3\n8 8\n6 7 2 1\n4 5 5 3\n5 6 1 3\n3 4 5 4\n2 3 2 3\n1 2 1 3\n5 1 2 9\n7 8 1 5\n", "output": "Game #1: Suckzoo ends game in time 12, earning 12 garnet(s).\nGame #2: Suckzoo ends game in time 5, earning 13 garnet(s).\nGame #3: Suckzoo ends game in time 8, earning 28 garnet(s).\n"}, {"input": "3\n5 7\n2 3 3 5\n1 2 3 4\n3 4 4 5\n1 3 4 2\n2 3 4 5\n3 4 4 2\n4 5 2 4\n4 4\n1 2 3 2\n3 4 4 4\n1 4 5 8\n2 3 2 1\n7 7\n4 5 3 3\n5 6 5 5\n1 2 1 5\n2 3 1 1\n2 3 3 5\n3 4 5 1\n6 7 5 4\n", "output": "Game #1: Suckzoo ends game in time 10, earning 11 garnet(s).\nGame #2: Suckzoo ends game in time 9, earning 7 garnet(s).\nGame #3: Suckzoo ends game in time 22, earning 29 garnet(s).\n"}, {"input": "3\n7 9\n2 6 1 1\n6 7 4 5\n4 6 1 2\n4 5 5 4\n5 6 1 1\n3 4 1 2\n1 2 1 5\n2 3 1 2\n7 1 4 3\n6 5\n2 3 5 4\n3 4 4 1\n4 5 1 1\n5 6 2 1\n1 2 5 5\n4 3\n2 3 4 3\n3 4 1 1\n1 2 1 2\n", "output": "Game #1: Suckzoo ends game in time 6, earning 13 garnet(s).\nGame #2: Suckzoo ends game in time 19, earning 14 garnet(s).\nGame #3: Suckzoo ends game in time 8, earning 10 garnet(s).\n"}]