{
  "id": 18991,
  "title": "Machine Learning",
  "time_limit": "4 초",
  "memory_limit": "256 MB",
  "description": "<p>Lately, Byton has found interest in the science describing methods of teaching computers identifying patterns in data and drawing conclusions from them -- <em>the machine learning</em>.</p>\n<p>During his research in this field, he had to investigate properties of some complicated function $f$. He computed its value in a number of points $x_1, x_2 \\dots, x_n$, obtaining results $y_1, y_2, \\dots, y_n$.</p>\n<p>He would like to approximate $f$ by some <strong>continuous</strong> function $g$, composed of two linear parts; formally for some $x \\in \\mathbb{R}$, $g$ should be linear for arguments less than $x$ and linear for arguments greater than $x$.</p>\n<p>Byton would like to achieve a faithful approximation of $f$. He would like to minimize the mean squared error:</p>\n<p>\\[\\frac1n \\sum_{i=1}^n (y_i - g(x_i))^2.\\]</p>",
  "input": "<p>The first line of the input contains a single integer $n$ ($1 \\le n \\le 100\\,000$). Each of the next $n$ lines contain two integers $x_i, y_i$ ($0 \\le x_i \\le 1\\,000\\,000$, $0 \\le y_i \\le 1000$). The numbers $x_i$ are pairwise different.</p>",
  "output": "<p>You should print a single real number -- the minimum possible mean squared error he is able to achieve.</p>\n<p>Your answer will be accepted if its absolute error does not exceed $1$.</p>",
  "samples": [
    {
      "input": "5\n0 1\n2 0\n1 3\n4 4\n3 2\n",
      "output": "0.8333333333333\n"
    },
    {
      "input": "7\n0 0\n1 1\n2 2\n3 4\n4 2\n5 1\n6 0\n",
      "output": "0.0659340659341\n"
    }
  ],
  "hint": "<p>In the first example, the optimal mean squared error is $\\frac56$. You can get it by fixing on the left the linear function $-\\frac{x}{2} + \\frac{11}6$ and on the right, the linear function $2x-4$.</p>\n<p style=\"text-align: center;\"><img alt=\"\" src=\"1.png\" style=\"width: 250px; height: 254px;\"/></p>\n<p>In the second example the minimum mean squared error is $\\frac{6}{91}$. The function can be constructed from lines $\\frac{16}{13}x - \\frac2{13}$ and $-\\frac{16}{13}x + \\frac{94}{13}$.</p>\n<p style=\"text-align: center;\"><img alt=\"\" src=\"2.png\" style=\"width: 250px; height: 186px;\"/></p>",
  "source": "Camp, Petrozavodsk Programming Camp, Summer 2018, Day 5: Warsaw U Contest, XVIII Open Cup named after E.V. Pankratiev Onsite",
  "level": 0,
  "tags": [],
  "accepted_user_count": 2,
  "submission_count": null,
  "average_tries": 4.5
}
