{
  "id": 7908,
  "title": "Will It Stop?",
  "time_limit": "3 초",
  "memory_limit": "64 MB",
  "description": "<p>Byteasar was wandering around the library of the University of Warsaw and at one of its facades he noticed a piece of a program with an inscription “Will it stop?”. The question seemed interesting, so Byteasar tried to tackle it after returning home. Unfortunately, when he was writing down the piece of code he made a mistake and noted:</p>\n<pre>\nwhile n &gt; 1 do\n  if n mod 2 = 0 then\n    n := n / 2\n  else\n    n := 3 · n + 3</pre>\n<p>Byteasar is now trying to figure out, for which initial values of the variable n the program he wrote down stops. We assume that the variable n has an unbounded size, i.e., it may attain arbitrarily large values.</p>",
  "input": "<p>The first and only line of input contains one integer n (2 ≤ n ≤ 10<sup>14</sup>).</p>",
  "output": "<p>In the first and only line of output you should write a single word TAK (i.e., yes in Polish), if the program stops for the given value of n, or NIE (no in Polish) otherwise.</p>",
  "samples": [
    {
      "input": "4\n",
      "output": "TAK\n"
    }
  ],
  "hint": null,
  "source": "ICPC, Regionals, Europe, Central European Regional Contest, Poland Collegiate Programming Contest, AMPPZ 2011",
  "level": 8,
  "tags": [
    "math"
  ],
  "accepted_user_count": 93,
  "submission_count": null,
  "average_tries": 1.5484000444412231
}