{
  "id": 17516,
  "title": "Minimum Diameter Spanning Tree",
  "time_limit": "5 초 (추가 시간 없음)",
  "memory_limit": "1024 MB",
  "description": "<p>You are given a simple connected undirected weighted graph $G$ with $N$ nodes and $M$ edges. Each node is numbered 1 through $N$.</p>\n<p>A spanning tree of $G$ is a subgraph of $G$, which is a tree and connects all the vertices of $G$. The diameter of a tree is the length of the longest path among the paths between any two nodes in the tree. A minimum diameter spanning tree of $G$ is a spanning tree of $G$ that has a minimum diameter.</p>\n<p>Write a program that finds any minimum diameter spanning tree.</p>",
  "input": "<p>The first line of the input contains two integers $N$ ($2 \\le N \\le 500$) and $M$ ($N-1 \\le M \\le \\frac{N(N-1)}{2}$).</p>\n<p>Then $M$ lines follow: The $i$ ($1 \\le i \\le M$)-th line contains three space-separated integers $u_i$, $v_i$ and $l_i$ ($1 \\le u_i, v_i \\le N$, $1 \\le l_i \\le 10^9$); it describes a bidirectional edge connecting vertex $u_i$ and vertex $v_i$ with length $l_i$.</p>\n<p>It is guaranteed that the given graph doesn't have any loops or multiple edges, and the graph is connected. </p>",
  "output": "<p>In the first line, print the diameter of the minimum diameter spanning tree of $G$. </p>\n<p>In the next $N-1$ lines, print the description of the edges in the minimum diameter spanning tree of $G$. The $j$ ($1 \\le j \\le N-1$)-th line should contain two space-separated integers $x_i$ and $y_i$ ($1 \\le x_i,\\ y_i \\le N$); it describes a bidirectional edge connecting vertex $x_i$ and $y_i$. </p>\n<p>If there are several possible answers, print any one of them.</p>",
  "samples": [
    {
      "input": "3 3\n1 2 1\n2 3 1\n3 1 1\n",
      "output": "2\n1 2\n3 1\n"
    },
    {
      "input": "6 7\n1 2 10\n2 3 20\n1 3 30\n3 4 1000\n4 5 30\n5 6 20\n4 6 10\n",
      "output": "1060\n3 4\n6 4\n5 6\n2 3\n1 2\n"
    }
  ],
  "hint": null,
  "source": "University, KAIST, KAIST ICPC Mock Competition, 2019 KAIST 9th ICPC Mock Competition, Contest, Open Cup, 2019/2020 Season, Stage 5: Grand Prix of Korea, koosaga, tncks0121",
  "level": 25,
  "tags": [
    "graphs",
    "shortest_path",
    "floyd_warshall",
    "traceback"
  ],
  "accepted_user_count": 21,
  "submission_count": null,
  "average_tries": 4.523799896240234
}