{
  "id": 4352,
  "title": "Jogging Trails",
  "time_limit": "1 초",
  "memory_limit": "128 MB",
  "description": "<p>Gord is training for a marathon. Behind his house is a park with a large network of jogging trails connecting water stations. Gord wants to find the shortest jogging route that travels along every trail at least once.</p>",
  "input": "<p>Input consists of several test cases. The first line of input for each case contains two positive integers: n &lt;= 15, the number of water stations, and m &lt; 1000, the number of trails. For each trail, there is one subsequent line of input containing three positive integers: the first two, between 1 and n, indicating the water stations at the end points of the trail; the third indicates the length of the trail, in cubits. There may be more than one trail between any two stations; each different trail is given only once in the input; each trail can be travelled in either direction. It is possible to reach any trail from any other trail by visiting a sequence of water stations connected by trails. Gord's route may start at any water station, and must end at the same station. A single line containing 0 follows the last test case.</p>",
  "output": "<p>For each case, there should be one line of output giving the length of Gord's jogging route.</p>",
  "samples": [
    {
      "input": "4 5\n1 2 3\n2 3 4\n3 4 5\n1 4 10\n1 3 12\n0\n",
      "output": "41\n"
    }
  ],
  "hint": null,
  "source": "Contest, Waterloo's local Programming Contests, 1 June, 2002",
  "level": 17,
  "tags": [
    "bitmask",
    "dp",
    "dp_bitfield",
    "eulerian_path",
    "graphs"
  ],
  "accepted_user_count": 6,
  "submission_count": null,
  "average_tries": 3.3333001136779785
}