{
  "id": 33506,
  "title": "Table Recovery",
  "time_limit": "2 초",
  "memory_limit": "2048 MB",
  "description": "<p>Bessie has an $N\\times N$ ($1\\le N\\le 1000$) addition table where the integer in the cell at row $r$ and column $c$ is $r+c$, for all $1\\le r,c\\le N$. For example, for $N=3$, the table would look like this:</p>\n<pre>\n2 3 4\n3 4 5\n4 5 6\n</pre>\n<p>Unfortunately, Elsie got ahold of the table and permuted it by performing the following three types of operations as many times as she wanted.</p>\n<ol>\n<li>Swap two rows</li>\n<li>Swap two columns</li>\n<li>Select two values $a$ and $b$ that are both present in the table, then simultaneously change every occurrence of $a$ to $b$ and every occurrence of $b$ to $a$.</li>\n</ol>\n<p>Elsie will always perform operations in increasing order of type; that is, she performs as many operations as she likes (possibly none) first of type $1$, then of type $2$, and finally of type $3$.</p>\n<p>Help Bessie recover a possible state of the table after Elsie finished applying all of her operations of types $1$ and $2$, but before applying any operations of type $3$. There may be multiple possible answers, in which case you should output the lexicographically smallest one.</p>\n<p>To compare two tables lexicographically, compare the first entries at which they differ, when reading both tables in the natural order (rows from top to bottom, left to right within a row).</p>",
  "input": "<p>The first line contains $N$.</p>\n<p>The next $N$ lines each contain $N$ integers, representing Bessie's addition table after Elsie has permuted it.</p>",
  "output": "<p>The lexicographically minimum possible state of the table after all operations of types 1 and 2, but before any operations of type 3. It is guaranteed that the answer exists.</p>",
  "samples": [
    {
      "input": "1\n2\n",
      "output": "2\n"
    },
    {
      "input": "3\n3 4 2\n5 2 3\n6 3 5\n",
      "output": "4 2 3\n5 3 4\n6 4 5\n"
    },
    {
      "input": "6\n8 10 5 6 7 4\n12 11 10 4 8 2\n5 4 6 7 9 8\n10 2 4 8 5 12\n6 8 7 9 3 5\n4 12 8 5 6 10\n",
      "output": "7 5 8 9 10 6\n4 2 5 6 7 3\n8 6 9 10 11 7\n5 3 6 7 8 4\n9 7 10 11 12 8\n6 4 7 8 9 5\n"
    }
  ],
  "hint": null,
  "source": "Olympiad, USA Computing Olympiad, 2024-2025 Season, USACO 2025 January Contest, Silver",
  "level": 17,
  "tags": ["math", "ad_hoc", "constructive"],
  "accepted_user_count": 58,
  "submission_count": null,
  "average_tries": 1.7069000005722046
}
